{
  "name": "compound-lines",
  "description": "Verify shapes with compound line styles (double, triple, etc.)",
  "tags": ["shape", "line", "compound"],
  "input": {
    "template": "../templates/blank.pptx",
    "output": "../__output__/compound-lines.pptx",
    "slides": [
      {
        "slideNumber": 1,
        "addShapes": [
          {
            "type": "rectangle",
            "x": 50,
            "y": 50,
            "width": 150,
            "height": 80,
            "fill": "FFFFFF",
            "lineColor": "4472C4",
            "lineWidth": 3,
            "lineCompound": "double",
            "text": "Double"
          },
          {
            "type": "rectangle",
            "x": 230,
            "y": 50,
            "width": 150,
            "height": 80,
            "fill": "FFFFFF",
            "lineColor": "70AD47",
            "lineWidth": 4,
            "lineCompound": "triple",
            "text": "Triple"
          },
          {
            "type": "rectangle",
            "x": 410,
            "y": 50,
            "width": 150,
            "height": 80,
            "fill": "FFFFFF",
            "lineColor": "ED7D31",
            "lineWidth": 4,
            "lineCompound": "thickThin",
            "text": "ThickThin"
          },
          {
            "type": "rectangle",
            "x": 50,
            "y": 170,
            "width": 150,
            "height": 80,
            "fill": "FFFFFF",
            "lineColor": "FFC000",
            "lineWidth": 4,
            "lineCompound": "thinThick",
            "text": "ThinThick"
          },
          {
            "type": "ellipse",
            "x": 230,
            "y": 170,
            "width": 150,
            "height": 100,
            "fill": "E7E6E6",
            "lineColor": "7030A0",
            "lineWidth": 5,
            "lineCompound": "double",
            "lineDash": "dash"
          }
        ]
      }
    ]
  },
  "expected": {
    "slides": [
      {
        "slideNumber": 1,
        "shapes": [
          { "index": -5, "type": "sp", "line": { "compound": "dbl" } },
          { "index": -4, "type": "sp", "line": { "compound": "tri" } },
          { "index": -3, "type": "sp", "line": { "compound": "thickThin" } },
          { "index": -2, "type": "sp", "line": { "compound": "thinThick" } },
          { "index": -1, "type": "sp", "line": { "compound": "dbl", "dashStyle": "dash" } }
        ]
      }
    ]
  }
}
